pyhub/__init__.py
pyhub/llm/__init__.py
pyhub/llm/__main__.py
pyhub/llm/anthropic.py
pyhub/llm/base.py
pyhub/llm/constants.py
pyhub/llm/display.py
pyhub/llm/exceptions.py
pyhub/llm/google.py
pyhub/llm/hub.py
pyhub/llm/json.py
pyhub/llm/mock.py
pyhub/llm/ollama.py
pyhub/llm/openai.py
pyhub/llm/resource_manager.py
pyhub/llm/retry.py
pyhub/llm/settings.py
pyhub/llm/tools.py
pyhub/llm/types.py
pyhub/llm/upstage.py
pyhub/llm/agents/__init__.py
pyhub/llm/agents/base.py
pyhub/llm/agents/react.py
pyhub/llm/agents/simple_template.py
pyhub/llm/agents/tools/__init__.py
pyhub/llm/agents/tools/calculator.py
pyhub/llm/agents/tools/file_reader.py
pyhub/llm/agents/tools/registry.py
pyhub/llm/agents/tools/schemas.py
pyhub/llm/agents/tools/web_search.py
pyhub/llm/cache/__init__.py
pyhub/llm/cache/base.py
pyhub/llm/cache/file.py
pyhub/llm/cache/memory.py
pyhub/llm/cache/utils.py
pyhub/llm/commands/__init__.py
pyhub/llm/commands/agent.py
pyhub/llm/commands/ask.py
pyhub/llm/commands/chat.py
pyhub/llm/commands/compare.py
pyhub/llm/commands/describe.py
pyhub/llm/commands/embed.py
pyhub/llm/commands/mcp_server.py
pyhub/llm/history/__init__.py
pyhub/llm/history/base.py
pyhub/llm/history/memory.py
pyhub/llm/history/sqlalchemy_backup.py
pyhub/llm/management/commands/__init__.py
pyhub/llm/mcp/__init__.py
pyhub/llm/mcp/client.py
pyhub/llm/mcp/config.py
pyhub/llm/mcp/config_loader.py
pyhub/llm/mcp/config_loader_class.py
pyhub/llm/mcp/configs.py
pyhub/llm/mcp/loader.py
pyhub/llm/mcp/multi_client.py
pyhub/llm/mcp/policies.py
pyhub/llm/mcp/transports.py
pyhub/llm/mcp/wrapper.py
pyhub/llm/mcp/servers/__init__.py
pyhub/llm/mcp/servers/__main__.py
pyhub/llm/mcp/servers/calculator.py
pyhub/llm/mcp/servers/greeting.py
pyhub/llm/templates/__init__.py
pyhub/llm/templates/engine.py
pyhub/llm/templates/prompt.py
pyhub/llm/templates/prompts/react/system.md
pyhub/llm/templates/prompts/react/user.md
pyhub/llm/tracing/__init__.py
pyhub/llm/tracing/base.py
pyhub/llm/tracing/langsmith.py
pyhub_llm-0.10.0.dist-info/METADATA
pyhub_llm-0.10.0.dist-info/WHEEL
pyhub_llm-0.10.0.dist-info/entry_points.txt
pyhub_llm-0.10.0.dist-info/licenses/LICENSE
pyhub_llm-0.10.0.dist-info/RECORD
