Metadata-Version: 2.4
Name: pyhub-llm
Version: 0.10.0
Summary: Standalone LLM library with support for multiple providers
Project-URL: Homepage, https://github.com/pyhub-kr/pyhub-llm
Project-URL: Documentation, https://github.com/pyhub-kr/pyhub-llm#readme
Project-URL: Repository, https://github.com/pyhub-kr/pyhub-llm
Project-URL: Issues, https://github.com/pyhub-kr/pyhub-llm/issues
Author-email: PyHub Team <me@pyhub.kr>
License: MIT
License-File: LICENSE
Keywords: agent,ai,anthropic,google,llm,mcp,ollama,openai,react
Classifier: Development Status :: 4 - Beta
Classifier: Intended Audience :: Developers
Classifier: License :: OSI Approved :: MIT License
Classifier: Programming Language :: Python :: 3
Classifier: Programming Language :: Python :: 3.10
Classifier: Programming Language :: Python :: 3.11
Classifier: Programming Language :: Python :: 3.12
Classifier: Programming Language :: Python :: 3.13
Classifier: Topic :: Scientific/Engineering :: Artificial Intelligence
Classifier: Topic :: Software Development :: Libraries :: Python Modules
Requires-Python: >=3.10
Requires-Dist: aiofiles>=23.0.0
Requires-Dist: httpx>=0.24.0
Requires-Dist: jinja2>=3.1.0
Requires-Dist: pillow>=10.0.0
Requires-Dist: pydantic>=2.0.0
Requires-Dist: python-dotenv>=1.0.0
Requires-Dist: rich>=13.0.0
Requires-Dist: toml>=0.10.0
Requires-Dist: typer>=0.9.0
Provides-Extra: all
Requires-Dist: aiofiles>=23.0.0; extra == 'all'
Requires-Dist: anthropic>=0.52.0; extra == 'all'
Requires-Dist: fastmcp; extra == 'all'
Requires-Dist: google-genai>=1.19.0; extra == 'all'
Requires-Dist: httpx>=0.24.0; extra == 'all'
Requires-Dist: mcp; extra == 'all'
Requires-Dist: ollama>=0.5.0; extra == 'all'
Requires-Dist: openai>=1.84.0; extra == 'all'
Requires-Dist: opentelemetry-api>=1.20.0; extra == 'all'
Requires-Dist: orjson>=3.9.0; extra == 'all'
Requires-Dist: pillow>=10.0.0; extra == 'all'
Requires-Dist: pymupdf; extra == 'all'
Requires-Dist: pymupdf>=1.23.0; extra == 'all'
Requires-Dist: pyyaml>=6.0.0; extra == 'all'
Requires-Dist: uvicorn; extra == 'all'
Provides-Extra: anthropic
Requires-Dist: anthropic>=0.52.0; extra == 'anthropic'
Provides-Extra: build
Requires-Dist: build; extra == 'build'
Requires-Dist: setuptools; extra == 'build'
Requires-Dist: twine; extra == 'build'
Requires-Dist: wheel; extra == 'build'
Provides-Extra: dev
Requires-Dist: black>=23.0.0; extra == 'dev'
Requires-Dist: mypy>=1.0.0; extra == 'dev'
Requires-Dist: pytest-asyncio>=0.21.0; extra == 'dev'
Requires-Dist: pytest-cov>=4.0.0; extra == 'dev'
Requires-Dist: pytest>=7.0.0; extra == 'dev'
Requires-Dist: ruff>=0.1.0; extra == 'dev'
Provides-Extra: docs
Requires-Dist: mkdocs-autorefs>=0.5.0; extra == 'docs'
Requires-Dist: mkdocs-git-revision-date-localized-plugin>=1.2.0; extra == 'docs'
Requires-Dist: mkdocs-glightbox; extra == 'docs'
Requires-Dist: mkdocs-literate-nav>=0.6.0; extra == 'docs'
Requires-Dist: mkdocs-material>=9.5.0; extra == 'docs'
Requires-Dist: mkdocs-minify-plugin>=0.7.0; extra == 'docs'
Requires-Dist: mkdocs-section-index>=0.3.0; extra == 'docs'
Requires-Dist: mkdocs>=1.5.0; extra == 'docs'
Requires-Dist: mkdocstrings[python]>=0.24.0; extra == 'docs'
Requires-Dist: pymdown-extensions>=10.0; extra == 'docs'
Provides-Extra: google
Requires-Dist: google-genai>=1.19.0; extra == 'google'
Provides-Extra: image
Requires-Dist: aiofiles>=23.0.0; extra == 'image'
Requires-Dist: pillow>=10.0.0; extra == 'image'
Provides-Extra: langsmith
Requires-Dist: httpx>=0.24.0; extra == 'langsmith'
Requires-Dist: orjson>=3.9.0; extra == 'langsmith'
Provides-Extra: mcp
Requires-Dist: fastmcp; extra == 'mcp'
Requires-Dist: mcp; extra == 'mcp'
Requires-Dist: pyyaml>=6.0.0; extra == 'mcp'
Requires-Dist: uvicorn; extra == 'mcp'
Provides-Extra: observability
Requires-Dist: httpx>=0.24.0; extra == 'observability'
Requires-Dist: opentelemetry-api>=1.20.0; extra == 'observability'
Requires-Dist: orjson>=3.9.0; extra == 'observability'
Provides-Extra: ollama
Requires-Dist: ollama>=0.5.0; extra == 'ollama'
Requires-Dist: pymupdf; extra == 'ollama'
Provides-Extra: openai
Requires-Dist: openai>=1.84.0; extra == 'openai'
Provides-Extra: pdf
Requires-Dist: pymupdf>=1.23.0; extra == 'pdf'
Provides-Extra: tracing
Requires-Dist: opentelemetry-api>=1.20.0; extra == 'tracing'
Provides-Extra: upstage
Requires-Dist: openai>=1.84.0; extra == 'upstage'
